zcmds/__init__.py
zcmds/cmds.txt
zcmds/get_cmds.py
zcmds/assets/bell.mp3
zcmds/cmds/__init__.py
zcmds/cmds/common/README.md
zcmds/cmds/common/__init__.py
zcmds/cmds/common/archive.py
zcmds/cmds/common/audnorm.py
zcmds/cmds/common/comports.py
zcmds/cmds/common/diskaudit.py
zcmds/cmds/common/docker_purge.py
zcmds/cmds/common/findfiles.py
zcmds/cmds/common/fixinternet.py
zcmds/cmds/common/geninvoice.py
zcmds/cmds/common/git_diff.py
zcmds/cmds/common/gitconfig.py
zcmds/cmds/common/gitsummary.py
zcmds/cmds/common/img2vid.py
zcmds/cmds/common/img2webp.py
zcmds/cmds/common/imgai.py
zcmds/cmds/common/imgcrop.py
zcmds/cmds/common/imgshrink.py
zcmds/cmds/common/lint.py
zcmds/cmds/common/losslesscut.py
zcmds/cmds/common/merge_to.py
zcmds/cmds/common/myip.py
zcmds/cmds/common/new.py
zcmds/cmds/common/obs_organize.py
zcmds/cmds/common/openaicfg.py
zcmds/cmds/common/pdf2png.py
zcmds/cmds/common/pdf2txt.py
zcmds/cmds/common/printenv.py
zcmds/cmds/common/pull.py
zcmds/cmds/common/push.py
zcmds/cmds/common/removebackground.py
zcmds/cmds/common/say.py
zcmds/cmds/common/search_and_replace.py
zcmds/cmds/common/search_in_files.py
zcmds/cmds/common/sharedir.py
zcmds/cmds/common/stereo2mono.py
zcmds/cmds/common/test.py
zcmds/cmds/common/trash.py
zcmds/cmds/common/trustdir.py
zcmds/cmds/common/tsdownloader.py
zcmds/cmds/common/vid2gif.py
zcmds/cmds/common/vid2jpg.py
zcmds/cmds/common/vid2mp3.py
zcmds/cmds/common/vid2mp4.py
zcmds/cmds/common/vid2webm.py
zcmds/cmds/common/vidcat.py
zcmds/cmds/common/vidclip.py
zcmds/cmds/common/viddur.py
zcmds/cmds/common/vidhero.py
zcmds/cmds/common/vidinfo.py
zcmds/cmds/common/vidlist.py
zcmds/cmds/common/vidmatrix.py
zcmds/cmds/common/vidmute.py
zcmds/cmds/common/vidshrink.py
zcmds/cmds/common/vidspeed.py
zcmds/cmds/common/vidvol.py
zcmds/cmds/common/vidwebmaster.py
zcmds/cmds/common/whichall.py
zcmds/cmds/common/yolo.py
zcmds/cmds/common/zcmds_main.py
zcmds/cmds/darwin/__init__.py
zcmds/cmds/darwin/test_net_connection.py
zcmds/cmds/linux/TODO
zcmds-1.5.34.dist-info/licenses/LICENSE
zcmds-1.5.34.dist-info/METADATA
zcmds-1.5.34.dist-info/WHEEL
zcmds-1.5.34.dist-info/entry_points.txt
zcmds-1.5.34.dist-info/top_level.txt
zcmds-1.5.34.dist-info/RECORD
