Metadata-Version: 2.4
Name: zcmds
Version: 1.5.34
Summary: Cross platform(ish) productivity commands written in python.
Home-page: https://github.com/zackees/zcmds
Maintainer: Zachary Vorhies
License: BSD 3-Clause License
Keywords: zcmds
Classifier: Programming Language :: Python :: 3
Requires-Python: >=3.10
License-File: LICENSE
Requires-Dist: ytclip
Requires-Dist: pdf2image
Requires-Dist: ffmpeg-normalize
Requires-Dist: appdirs
Requires-Dist: PyQt6
Requires-Dist: PyPDF2
Requires-Dist: jsoncomment
Requires-Dist: pyserial
Requires-Dist: openai>=1.3.7
Requires-Dist: anthropic>=0.21.0
Requires-Dist: consolemd
Requires-Dist: inputimeout
Requires-Dist: download
Requires-Dist: playaudio>=1.0.5
Requires-Dist: gTTS
Requires-Dist: py7zr
Requires-Dist: static-ffmpeg>=2.5
Requires-Dist: zcmds_win32>=1.2.12; platform_system == "Windows"
Requires-Dist: static-sox
Requires-Dist: json5
Requires-Dist: pipx
Requires-Dist: GitPython
Requires-Dist: transcribe-anything>=2.7.27
Requires-Dist: send2trash
Requires-Dist: magic-wormhole
Requires-Dist: wormhole-tx
Requires-Dist: pillow-heif
Requires-Dist: advanced-aicode>=1.1.0
Requires-Dist: advanced-askai
Requires-Dist: pywinpty; platform_system == "Windows"
Requires-Dist: codeup>=1.0.1
Dynamic: home-page
Dynamic: license-file
Dynamic: maintainer
